com_interface/__init__.py
com_interface/ip_utils.py
com_interface/serial_base.py
com_interface/serial_cobs.py
com_interface/serial_dle.py
com_interface/tcp.py
com_interface/udp.py
com_interface-0.2.0.dist-info/licenses/LICENSE
com_interface-0.2.0.dist-info/licenses/NOTICE
com_interface-0.2.0.dist-info/METADATA
com_interface-0.2.0.dist-info/WHEEL
com_interface-0.2.0.dist-info/top_level.txt
com_interface-0.2.0.dist-info/RECORD
