Metadata-Version: 2.4
Name: com-interface
Version: 0.2.0
Summary: Generic communication interface abstraction for sending and receiving arbitrary byte packets
Author-email: Robin Mueller <robin.mueller.m@gmail.com>
License: Apache-2.0
Project-URL: Homepage, https://github.com/us-irs/com-interface
Keywords: communication,packet,abstraction,serial
Classifier: Development Status :: 5 - Production/Stable
Classifier: License :: OSI Approved :: Apache Software License
Classifier: Natural Language :: English
Classifier: Operating System :: POSIX
Classifier: Operating System :: Microsoft :: Windows
Classifier: Programming Language :: Python :: 3
Classifier: Programming Language :: Python :: 3.8
Classifier: Programming Language :: Python :: 3.9
Classifier: Topic :: Communications
Classifier: Topic :: Software Development :: Libraries
Classifier: Topic :: Software Development :: Libraries :: Python Modules
Classifier: Topic :: Scientific/Engineering
Requires-Python: >=3.9
License-File: LICENSE
License-File: NOTICE
Requires-Dist: crcmod~=1.7
Requires-Dist: pyserial~=3.5
Requires-Dist: cobs~=1.2
Requires-Dist: dle-encoder~=0.2.3
Provides-Extra: test
Requires-Dist: pytest~=8.3; extra == "test"
Requires-Dist: spacepackets~=0.28.0; extra == "test"
Dynamic: license-file
